moss/__init__.py
moss/__main__.py
moss/canonical.py
moss/cli.py
moss/crypto.py
moss/encoding.py
moss/envelope.py
moss/errors.py
moss/keystore.py
moss/sequence.py
moss/subject.py
moss_sdk-0.1.2.dist-info/METADATA
moss_sdk-0.1.2.dist-info/WHEEL
moss_sdk-0.1.2.dist-info/entry_points.txt
moss_sdk-0.1.2.dist-info/RECORD
