Metadata-Version: 2.4
Name: moss-sdk
Version: 0.1.2
Summary: Cryptographic identity and signed outputs for AI agents
Project-URL: Homepage, https://mosscomputing.com
Project-URL: Repository, https://github.com/mosscomputing/moss
Author: Carey D'Souza
License-Expression: MIT
Keywords: agents,ai,cryptography,identity,post-quantum,signing
Classifier: Development Status :: 3 - Alpha
Classifier: Intended Audience :: Developers
Classifier: License :: OSI Approved :: MIT License
Classifier: Programming Language :: Python :: 3
Classifier: Programming Language :: Python :: 3.9
Classifier: Programming Language :: Python :: 3.10
Classifier: Programming Language :: Python :: 3.11
Classifier: Programming Language :: Python :: 3.12
Requires-Python: >=3.9
Requires-Dist: cryptography>=41.0.0
Requires-Dist: dilithium-py>=0.1.0
Provides-Extra: dev
Requires-Dist: pytest-cov>=4.0.0; extra == 'dev'
Requires-Dist: pytest>=7.0.0; extra == 'dev'
